videoembed/__init__.py
videoembed/embedder.py
videoembed/exceptions.py
videoembed/providers/__init__.py
videoembed/providers/base.py
videoembed/providers/config.py
videoembed/providers/vimeo.py
videoembed/providers/youtube.py
videoembed/tests/__init__.py
videoembed/tests/test_embedder.py
videoembed/tests/test_providers_vimeo.py
videoembed/tests/test_providers_youtube.py
videoembed-1.0.3.dist-info/LICENSE
videoembed-1.0.3.dist-info/METADATA
videoembed-1.0.3.dist-info/WHEEL
videoembed-1.0.3.dist-info/top_level.txt
videoembed-1.0.3.dist-info/RECORD
