Metadata-Version: 2.1
Name: videoembed
Version: 1.0.3
Summary: Create embed codes from video URLs.
Home-page: https://github.com/phewera/videoembed
Author: Philipp Hewera
Author-email: Philipp Hewera <github.hewera@mailbox.org>
License: GNU GENERAL PUBLIC LICENSE
Project-URL: Homepage, https://github.com/phewera/videoembed
Keywords: oembed,video,embed codes,youtube,vimeo,video embedder
Classifier: Programming Language :: Python :: 3
Classifier: License :: OSI Approved :: GNU General Public License v3 (GPLv3)
Classifier: Operating System :: OS Independent
Requires-Python: >=3.8
License-File: LICENSE
Requires-Dist: requests >=2.31.0
